django_tokenapi-2.1.1.dist-info/licenses/LICENSE
tokenapi/__init__.py
tokenapi/backends.py
tokenapi/decorators.py
tokenapi/http.py
tokenapi/tokens.py
tokenapi/urls.py
tokenapi/views.py
django_tokenapi-2.1.1.dist-info/METADATA
django_tokenapi-2.1.1.dist-info/WHEEL
django_tokenapi-2.1.1.dist-info/top_level.txt
django_tokenapi-2.1.1.dist-info/RECORD
