Metadata-Version: 2.4
Name: django-tokenapi
Version: 2.1.1
Summary: Add an API to your Django app using token-based authentication.
Home-page: https://github.com/jpulgarin/django-tokenapi
Author: Julian Pulgarín
License: MIT
Classifier: Programming Language :: Python :: 3
License-File: LICENSE
Requires-Dist: Django>=2.0
Dynamic: author
Dynamic: classifier
Dynamic: description
Dynamic: description-content-type
Dynamic: home-page
Dynamic: license
Dynamic: license-file
Dynamic: requires-dist
Dynamic: summary
